agromet/__init__.py
agromet/agromet.py
agromet-0.0.1.dist-info/LICENCE
agromet-0.0.1.dist-info/METADATA
agromet-0.0.1.dist-info/WHEEL
agromet-0.0.1.dist-info/top_level.txt
agromet-0.0.1.dist-info/RECORD
