Metadata-Version: 2.1
Name: agromet
Version: 0.0.1
Summary: Cálculos agrometeorológicos
Author: Rafael Lima
Author-email: rf.lima@unesp.br
License: MIT License
Keywords: agromet
License-File: LICENCE
Requires-Dist: numpy
